lightningchart_trader/__init__.py
lightningchart_trader/heatmap.py
lightningchart_trader/instance.py
lightningchart_trader/kagi.py
lightningchart_trader/menu_options.py
lightningchart_trader/point_and_figure.py
lightningchart_trader/renko.py
lightningchart_trader/technical_analysis_methods.py
lightningchart_trader/trader.py
lightningchart_trader/drawing_tools/__init__.py
lightningchart_trader/drawing_tools/arrow.py
lightningchart_trader/drawing_tools/cross_line.py
lightningchart_trader/drawing_tools/cycle_lines.py
lightningchart_trader/drawing_tools/date_range.py
lightningchart_trader/drawing_tools/elliot_wave.py
lightningchart_trader/drawing_tools/ellipse.py
lightningchart_trader/drawing_tools/extended_line.py
lightningchart_trader/drawing_tools/fibonacci_arc.py
lightningchart_trader/drawing_tools/fibonacci_extension.py
lightningchart_trader/drawing_tools/fibonacci_fan.py
lightningchart_trader/drawing_tools/fibonacci_retracements.py
lightningchart_trader/drawing_tools/fibonacci_time_zones.py
lightningchart_trader/drawing_tools/flat_top_bottom.py
lightningchart_trader/drawing_tools/gannbox.py
lightningchart_trader/drawing_tools/gannfan.py
lightningchart_trader/drawing_tools/head_and_shoulders.py
lightningchart_trader/drawing_tools/horizontal_line.py
lightningchart_trader/drawing_tools/horizontal_ray.py
lightningchart_trader/drawing_tools/linear_regression_channel.py
lightningchart_trader/drawing_tools/parallel_channel.py
lightningchart_trader/drawing_tools/pitchfork.py
lightningchart_trader/drawing_tools/plain_text.py
lightningchart_trader/drawing_tools/price_range.py
lightningchart_trader/drawing_tools/rectangle.py
lightningchart_trader/drawing_tools/sine_wave.py
lightningchart_trader/drawing_tools/text_box.py
lightningchart_trader/drawing_tools/trend_line.py
lightningchart_trader/drawing_tools/triangle.py
lightningchart_trader/drawing_tools/vertical_line.py
lightningchart_trader/drawing_tools/xabcd_pattern.py
lightningchart_trader/helper_routines/__init__.py
lightningchart_trader-1.1.0.dist-info/METADATA
lightningchart_trader-1.1.0.dist-info/WHEEL
lightningchart_trader-1.1.0.dist-info/top_level.txt
lightningchart_trader-1.1.0.dist-info/RECORD
