Metadata-Version: 2.4
Name: lightningchart_trader
Version: 1.1.0
Summary: An interactive high-performance charting library for financial data visualization and technical analysis
Home-page: https://lightningchart.com/python-charts/trader/
Author: LightningChart Ltd.
Author-email: lightningchart@lightningchart.com
Classifier: Programming Language :: Python :: 3
Classifier: Operating System :: OS Independent
Requires-Python: >=3.10
Requires-Dist: Flask>=3.0.3
Requires-Dist: Flask_SocketIO>=5.4.1
Requires-Dist: gevent>=24.10.3
Requires-Dist: gevent-websocket>=0.10.1
Requires-Dist: msgpack>=1.1.0
Requires-Dist: requests
Requires-Dist: ipython
Requires-Dist: pandas
Dynamic: author
Dynamic: author-email
Dynamic: classifier
Dynamic: description
Dynamic: description-content-type
Dynamic: home-page
Dynamic: requires-dist
Dynamic: requires-python
Dynamic: summary
